oswaveplayer/__init__.py
oswaveplayer/oswaveplayer.py
oswaveplayer-0.3.0.dist-info/LICENSE
oswaveplayer-0.3.0.dist-info/METADATA
oswaveplayer-0.3.0.dist-info/WHEEL
oswaveplayer-0.3.0.dist-info/top_level.txt
oswaveplayer-0.3.0.dist-info/RECORD
