Metadata-Version: 2.1
Name: oswaveplayer
Version: 0.3.0
Summary: This is a simple wave player that uses command line instructions to the OS to play .wav files.
Home-page: https://github.com/garydavenport73/OSWavePlayer
Author: Gary Davenport
Author-email: dovedweller@gmail.com
License: UNKNOWN
Project-URL: Bug Tracker, https://github.com/garydavenport73/OSWavePlayer/issues
Platform: UNKNOWN
Classifier: Programming Language :: Python :: 3
Classifier: License :: OSI Approved :: MIT License
Classifier: Operating System :: OS Independent
Requires-Python: >=3.6
License-File: LICENSE
